{
  "generated_at": "2026-05-02T08:21:13.886Z",
  "report": [
    {
      "wallet": "0x020c5bb0d81b8cf539ca06364ece4a41631995b4",
      "whale": "Avant",
      "chain": "avax",
      "debank_usd": 0.000028717573197192174,
      "modeled_usd": 0,
      "delta_usd": 0.000028717573197192174,
      "active_for_position_scan": false,
      "scan_threshold_usd": 50000,
      "below_threshold": true,
      "classification": "below-threshold",
      "protocols_missing_or_misaligned": []
    },
    {
      "wallet": "0x020c5bb0d81b8cf539ca06364ece4a41631995b4",
      "whale": "Avant",
      "chain": "eth",
      "debank_usd": 0.0019177070922201337,
      "modeled_usd": 0,
      "delta_usd": 0.0019177070922201337,
      "active_for_position_scan": false,
      "scan_threshold_usd": 50000,
      "below_threshold": true,
      "classification": "below-threshold",
      "protocols_missing_or_misaligned": []
    },
    {
      "wallet": "0x887fd380c1e4cc28e119917015fe7fb0062c5d67",
      "whale": "Avant",
      "chain": "avax",
      "debank_usd": 483.36564388109304,
      "modeled_usd": 0,
      "delta_usd": 483.36564388109304,
      "active_for_position_scan": false,
      "scan_threshold_usd": 50000,
      "below_threshold": true,
      "classification": "below-threshold",
      "protocols_missing_or_misaligned": []
    },
    {
      "wallet": "0x887fd380c1e4cc28e119917015fe7fb0062c5d67",
      "whale": "Avant",
      "chain": "eth",
      "debank_usd": 15.164080689577794,
      "modeled_usd": 0,
      "delta_usd": 15.164080689577794,
      "active_for_position_scan": false,
      "scan_threshold_usd": 50000,
      "below_threshold": true,
      "classification": "below-threshold",
      "protocols_missing_or_misaligned": []
    },
    {
      "wallet": "0x1ae4190c55c2986130694af6998a94126c0685cd",
      "whale": "Avant",
      "chain": "plume",
      "debank_usd": 0,
      "modeled_usd": 0,
      "delta_usd": 0,
      "active_for_position_scan": false,
      "scan_threshold_usd": 50000,
      "below_threshold": true,
      "classification": "below-threshold",
      "protocols_missing_or_misaligned": []
    },
    {
      "wallet": "0x1ae4190c55c2986130694af6998a94126c0685cd",
      "whale": "Avant",
      "chain": "eth",
      "debank_usd": 0.00539601910372534,
      "modeled_usd": 0,
      "delta_usd": 0.00539601910372534,
      "active_for_position_scan": false,
      "scan_threshold_usd": 50000,
      "below_threshold": true,
      "classification": "below-threshold",
      "protocols_missing_or_misaligned": []
    },
    {
      "wallet": "0xc1d023141ad6935f81e5286e577768b75c9ff8eb",
      "whale": "Avant",
      "chain": "bera",
      "debank_usd": 2.7466136928650906,
      "modeled_usd": 0,
      "delta_usd": 2.7466136928650906,
      "active_for_position_scan": false,
      "scan_threshold_usd": 50000,
      "below_threshold": true,
      "classification": "below-threshold",
      "protocols_missing_or_misaligned": []
    },
    {
      "wallet": "0xc1d023141ad6935f81e5286e577768b75c9ff8eb",
      "whale": "Avant",
      "chain": "eth",
      "debank_usd": 1.1394346634663466e-18,
      "modeled_usd": 0,
      "delta_usd": 1.1394346634663466e-18,
      "active_for_position_scan": false,
      "scan_threshold_usd": 50000,
      "below_threshold": true,
      "classification": "below-threshold",
      "protocols_missing_or_misaligned": []
    },
    {
      "wallet": "0xfbbf1826aba90704a2167d2eb4a7a9d83a8de9c7",
      "whale": "Avant",
      "chain": "eth",
      "debank_usd": 1.2878516430232492,
      "modeled_usd": 0,
      "delta_usd": 1.2878516430232492,
      "active_for_position_scan": false,
      "scan_threshold_usd": 50000,
      "below_threshold": true,
      "classification": "below-threshold",
      "protocols_missing_or_misaligned": []
    },
    {
      "wallet": "0x1dff1e9968222aa6c66bf402bac2c3fe5ed13f76",
      "whale": "Avant",
      "chain": "bsc",
      "debank_usd": 3.9453707633376203,
      "modeled_usd": 0,
      "delta_usd": 3.9453707633376203,
      "active_for_position_scan": false,
      "scan_threshold_usd": 50000,
      "below_threshold": true,
      "classification": "below-threshold",
      "protocols_missing_or_misaligned": []
    },
    {
      "wallet": "0x1dff1e9968222aa6c66bf402bac2c3fe5ed13f76",
      "whale": "Avant",
      "chain": "eth",
      "debank_usd": 92.55545203176902,
      "modeled_usd": 0,
      "delta_usd": 92.55545203176902,
      "active_for_position_scan": false,
      "scan_threshold_usd": 50000,
      "below_threshold": true,
      "classification": "below-threshold",
      "protocols_missing_or_misaligned": []
    },
    {
      "wallet": "0x3207363359ca0c11d11073ad48301e8c958b7910",
      "whale": "Avant",
      "chain": "eth",
      "debank_usd": 10.264867751196299,
      "modeled_usd": 0,
      "delta_usd": 10.264867751196299,
      "active_for_position_scan": false,
      "scan_threshold_usd": 50000,
      "below_threshold": true,
      "classification": "below-threshold",
      "protocols_missing_or_misaligned": []
    },
    {
      "wallet": "0x3207363359ca0c11d11073ad48301e8c958b7910",
      "whale": "Avant",
      "chain": "mnt",
      "debank_usd": 8468005.114917323,
      "modeled_usd": 8705455.483961388,
      "delta_usd": -237450.36904406548,
      "active_for_position_scan": true,
      "scan_threshold_usd": 50000,
      "below_threshold": false,
      "classification": "needs-review",
      "protocols_missing_or_misaligned": [
        {
          "protocol": "aave",
          "debank_usd": 8468005.114917323,
          "modeled_usd": 8705455.483961388,
          "delta_usd": -237450.36904406548
        }
      ]
    },
    {
      "wallet": "0x7bee8d37fba61a6251a08b957d502c56e2a50fab",
      "whale": "Avant",
      "chain": "arb",
      "debank_usd": 272.81542647912215,
      "modeled_usd": 0,
      "delta_usd": 272.81542647912215,
      "active_for_position_scan": false,
      "scan_threshold_usd": 50000,
      "below_threshold": true,
      "classification": "below-threshold",
      "protocols_missing_or_misaligned": []
    },
    {
      "wallet": "0x7bee8d37fba61a6251a08b957d502c56e2a50fab",
      "whale": "Avant",
      "chain": "bera",
      "debank_usd": 16.773647513619217,
      "modeled_usd": 0,
      "delta_usd": 16.773647513619217,
      "active_for_position_scan": false,
      "scan_threshold_usd": 50000,
      "below_threshold": true,
      "classification": "below-threshold",
      "protocols_missing_or_misaligned": []
    },
    {
      "wallet": "0x7bee8d37fba61a6251a08b957d502c56e2a50fab",
      "whale": "Avant",
      "chain": "eth",
      "debank_usd": 4145633.9573172485,
      "modeled_usd": 4153233.9796619993,
      "delta_usd": -7600.022344750818,
      "active_for_position_scan": true,
      "scan_threshold_usd": 50000,
      "below_threshold": false,
      "classification": "needs-review",
      "protocols_missing_or_misaligned": [
        {
          "protocol": "morpho",
          "debank_usd": 4145549.3296690136,
          "modeled_usd": 4153233.9796619993,
          "delta_usd": -7684.649992985651
        }
      ]
    },
    {
      "wallet": "0x7bee8d37fba61a6251a08b957d502c56e2a50fab",
      "whale": "Avant",
      "chain": "plasma",
      "debank_usd": 7.528134864645962,
      "modeled_usd": 0,
      "delta_usd": 7.528134864645962,
      "active_for_position_scan": false,
      "scan_threshold_usd": 50000,
      "below_threshold": true,
      "classification": "below-threshold",
      "protocols_missing_or_misaligned": []
    },
    {
      "wallet": "0x7bee8d37fba61a6251a08b957d502c56e2a50fab",
      "whale": "Avant",
      "chain": "sei",
      "debank_usd": 10.782118681133042,
      "modeled_usd": 0,
      "delta_usd": 10.782118681133042,
      "active_for_position_scan": false,
      "scan_threshold_usd": 50000,
      "below_threshold": true,
      "classification": "below-threshold",
      "protocols_missing_or_misaligned": []
    },
    {
      "wallet": "0x920eefbcf1f5756109952e6ff6da1cab950c64d7",
      "whale": "Avant",
      "chain": "eth",
      "debank_usd": 72.10702239518788,
      "modeled_usd": 0,
      "delta_usd": 72.10702239518788,
      "active_for_position_scan": false,
      "scan_threshold_usd": 50000,
      "below_threshold": true,
      "classification": "below-threshold",
      "protocols_missing_or_misaligned": []
    },
    {
      "wallet": "0x920eefbcf1f5756109952e6ff6da1cab950c64d7",
      "whale": "Avant",
      "chain": "megaeth",
      "debank_usd": 35859419.0612104,
      "modeled_usd": 0,
      "delta_usd": 35859419.0612104,
      "active_for_position_scan": true,
      "scan_threshold_usd": 50000,
      "below_threshold": false,
      "classification": "needs-review",
      "protocols_missing_or_misaligned": [
        {
          "protocol": "megaeth_aave3",
          "debank_usd": 35859419.0612104,
          "modeled_usd": 0,
          "delta_usd": 35859419.0612104
        }
      ]
    },
    {
      "wallet": "0x920eefbcf1f5756109952e6ff6da1cab950c64d7",
      "whale": "Avant",
      "chain": "mnt",
      "debank_usd": 1.945574315815879,
      "modeled_usd": 0,
      "delta_usd": 1.945574315815879,
      "active_for_position_scan": false,
      "scan_threshold_usd": 50000,
      "below_threshold": true,
      "classification": "below-threshold",
      "protocols_missing_or_misaligned": []
    },
    {
      "wallet": "0xd2305803ca7821e4e5c3bcaed366ad7de9f13739",
      "whale": "Avant",
      "chain": "eth",
      "debank_usd": 33.09524299721497,
      "modeled_usd": 0,
      "delta_usd": 33.09524299721497,
      "active_for_position_scan": false,
      "scan_threshold_usd": 50000,
      "below_threshold": true,
      "classification": "below-threshold",
      "protocols_missing_or_misaligned": []
    },
    {
      "wallet": "0xc2d2c22f54c9fae2456b6e7f7fbdc240e1898da1",
      "whale": "Avant",
      "chain": "sonic",
      "debank_usd": 571.0615390428986,
      "modeled_usd": 0,
      "delta_usd": 571.0615390428986,
      "active_for_position_scan": false,
      "scan_threshold_usd": 50000,
      "below_threshold": true,
      "classification": "below-threshold",
      "protocols_missing_or_misaligned": []
    },
    {
      "wallet": "0xacabc577f359e4af4dd057af56de5a576ba9bd82",
      "whale": "Avant",
      "chain": "avax",
      "debank_usd": 5.4582662373918195e-14,
      "modeled_usd": 0,
      "delta_usd": 5.4582662373918195e-14,
      "active_for_position_scan": false,
      "scan_threshold_usd": 50000,
      "below_threshold": true,
      "classification": "below-threshold",
      "protocols_missing_or_misaligned": []
    },
    {
      "wallet": "0xc468315a2df54f9c076bd5cfe5002ba211f74ca6",
      "whale": "Avant",
      "chain": "eth",
      "debank_usd": 12263034.383252257,
      "modeled_usd": 12298312.888240397,
      "delta_usd": -35278.504988139495,
      "active_for_position_scan": true,
      "scan_threshold_usd": 50000,
      "below_threshold": false,
      "classification": "needs-review",
      "protocols_missing_or_misaligned": [
        {
          "protocol": "aave",
          "debank_usd": 12263034.26227013,
          "modeled_usd": 12298312.888240397,
          "delta_usd": -35278.62597026676
        }
      ]
    },
    {
      "wallet": "0xc468315a2df54f9c076bd5cfe5002ba211f74ca6",
      "whale": "Avant",
      "chain": "hyper",
      "debank_usd": 5.667141892467509e-11,
      "modeled_usd": 0,
      "delta_usd": 5.667141892467509e-11,
      "active_for_position_scan": false,
      "scan_threshold_usd": 50000,
      "below_threshold": true,
      "classification": "below-threshold",
      "protocols_missing_or_misaligned": []
    },
    {
      "wallet": "0xc468315a2df54f9c076bd5cfe5002ba211f74ca6",
      "whale": "Avant",
      "chain": "ink",
      "debank_usd": 6220.147782750355,
      "modeled_usd": 0,
      "delta_usd": 6220.147782750355,
      "active_for_position_scan": false,
      "scan_threshold_usd": 50000,
      "below_threshold": true,
      "classification": "below-threshold",
      "protocols_missing_or_misaligned": [
        {
          "protocol": "aave",
          "debank_usd": 6220.147782750355,
          "modeled_usd": 0,
          "delta_usd": 6220.147782750355
        }
      ]
    },
    {
      "wallet": "0xc468315a2df54f9c076bd5cfe5002ba211f74ca6",
      "whale": "Avant",
      "chain": "megaeth",
      "debank_usd": 5101777.102577299,
      "modeled_usd": 0,
      "delta_usd": 5101777.102577299,
      "active_for_position_scan": true,
      "scan_threshold_usd": 50000,
      "below_threshold": false,
      "classification": "needs-review",
      "protocols_missing_or_misaligned": [
        {
          "protocol": "megaeth_aave3",
          "debank_usd": 5101777.102577299,
          "modeled_usd": 0,
          "delta_usd": 5101777.102577299
        }
      ]
    },
    {
      "wallet": "0xc468315a2df54f9c076bd5cfe5002ba211f74ca6",
      "whale": "Avant",
      "chain": "plasma",
      "debank_usd": 17633261.326313823,
      "modeled_usd": 17678598.167981595,
      "delta_usd": -45336.84166777134,
      "active_for_position_scan": true,
      "scan_threshold_usd": 50000,
      "below_threshold": false,
      "classification": "needs-review",
      "protocols_missing_or_misaligned": [
        {
          "protocol": "aave",
          "debank_usd": 17633261.326313823,
          "modeled_usd": 17678598.167981595,
          "delta_usd": -45336.84166777134
        }
      ]
    },
    {
      "wallet": "0x33a4866bffc90791e65da0d339eddcae3d9ce9f9",
      "whale": "Avant",
      "chain": "eth",
      "debank_usd": 0.022355824442533215,
      "modeled_usd": 0,
      "delta_usd": 0.022355824442533215,
      "active_for_position_scan": false,
      "scan_threshold_usd": 50000,
      "below_threshold": true,
      "classification": "below-threshold",
      "protocols_missing_or_misaligned": []
    },
    {
      "wallet": "0x0000000f2eb9f69274678c76222b35eec7588a65",
      "whale": "yoUSD",
      "chain": "eth",
      "debank_usd": 3124006.295673323,
      "modeled_usd": 3969802.139882121,
      "delta_usd": -845795.8442087979,
      "active_for_position_scan": true,
      "scan_threshold_usd": 50000,
      "below_threshold": false,
      "classification": "needs-review",
      "protocols_missing_or_misaligned": [
        {
          "protocol": "morpho",
          "debank_usd": 3123552.9768012688,
          "modeled_usd": 0,
          "delta_usd": 3123552.9768012688
        }
      ]
    },
    {
      "wallet": "0x0000000f2eb9f69274678c76222b35eec7588a65",
      "whale": "yoUSD",
      "chain": "arb",
      "debank_usd": 0.7317470657284868,
      "modeled_usd": 0,
      "delta_usd": 0.7317470657284868,
      "active_for_position_scan": false,
      "scan_threshold_usd": 50000,
      "below_threshold": true,
      "classification": "below-threshold",
      "protocols_missing_or_misaligned": []
    },
    {
      "wallet": "0x0000000f2eb9f69274678c76222b35eec7588a65",
      "whale": "yoUSD",
      "chain": "base",
      "debank_usd": 142.74249654145703,
      "modeled_usd": 18645947.9307477,
      "delta_usd": -18645805.188251156,
      "active_for_position_scan": false,
      "scan_threshold_usd": 50000,
      "below_threshold": true,
      "classification": "below-threshold",
      "protocols_missing_or_misaligned": []
    },
    {
      "wallet": "0x0000000f2eb9f69274678c76222b35eec7588a65",
      "whale": "yoUSD",
      "chain": "hyper",
      "debank_usd": 179.4270960872922,
      "modeled_usd": 0,
      "delta_usd": 179.4270960872922,
      "active_for_position_scan": false,
      "scan_threshold_usd": 50000,
      "below_threshold": true,
      "classification": "below-threshold",
      "protocols_missing_or_misaligned": []
    },
    {
      "wallet": "0x0000000f2eb9f69274678c76222b35eec7588a65",
      "whale": "yoUSD",
      "chain": "op",
      "debank_usd": 251.78149700699493,
      "modeled_usd": 0,
      "delta_usd": 251.78149700699493,
      "active_for_position_scan": false,
      "scan_threshold_usd": 50000,
      "below_threshold": true,
      "classification": "below-threshold",
      "protocols_missing_or_misaligned": []
    },
    {
      "wallet": "0x0000000f2eb9f69274678c76222b35eec7588a65",
      "whale": "yoUSD",
      "chain": "plasma",
      "debank_usd": 4.24785509345041,
      "modeled_usd": 0,
      "delta_usd": 4.24785509345041,
      "active_for_position_scan": false,
      "scan_threshold_usd": 50000,
      "below_threshold": true,
      "classification": "below-threshold",
      "protocols_missing_or_misaligned": []
    },
    {
      "wallet": "0x0000000f2eb9f69274678c76222b35eec7588a65",
      "whale": "yoUSD",
      "chain": "uni",
      "debank_usd": 5.681086990269594,
      "modeled_usd": 0,
      "delta_usd": 5.681086990269594,
      "active_for_position_scan": false,
      "scan_threshold_usd": 50000,
      "below_threshold": true,
      "classification": "below-threshold",
      "protocols_missing_or_misaligned": []
    },
    {
      "wallet": "0x815f5bb257e88b67216a344c7c83a3ea4ee74748",
      "whale": "Yuzu",
      "chain": "eth",
      "debank_usd": 9651710.209917197,
      "modeled_usd": 5495052.980397133,
      "delta_usd": 4156657.229520064,
      "active_for_position_scan": true,
      "scan_threshold_usd": 50000,
      "below_threshold": false,
      "classification": "needs-review",
      "protocols_missing_or_misaligned": [
        {
          "protocol": "sky",
          "debank_usd": 3017700.5516152983,
          "modeled_usd": 0,
          "delta_usd": 3017700.5516152983
        },
        {
          "protocol": "aave",
          "debank_usd": 1529283.7457917754,
          "modeled_usd": 0,
          "delta_usd": 1529283.7457917754
        },
        {
          "protocol": "morpho",
          "debank_usd": 1187249.2030781992,
          "modeled_usd": 1582591.4487811998,
          "delta_usd": -395342.2457030006
        }
      ]
    },
    {
      "wallet": "0x815f5bb257e88b67216a344c7c83a3ea4ee74748",
      "whale": "Yuzu",
      "chain": "arb",
      "debank_usd": 453515.7584070456,
      "modeled_usd": 455023.07820625976,
      "delta_usd": -1507.3197992141359,
      "active_for_position_scan": true,
      "scan_threshold_usd": 50000,
      "below_threshold": false,
      "classification": "needs-review",
      "protocols_missing_or_misaligned": [
        {
          "protocol": "arb_morphoblue",
          "debank_usd": 453515.7584070456,
          "modeled_usd": 0,
          "delta_usd": 453515.7584070456
        }
      ]
    },
    {
      "wallet": "0x815f5bb257e88b67216a344c7c83a3ea4ee74748",
      "whale": "Yuzu",
      "chain": "base",
      "debank_usd": 709550.6842323625,
      "modeled_usd": 711189.7734735599,
      "delta_usd": -1639.0892411973327,
      "active_for_position_scan": true,
      "scan_threshold_usd": 50000,
      "below_threshold": false,
      "classification": "aligned",
      "protocols_missing_or_misaligned": []
    },
    {
      "wallet": "0x815f5bb257e88b67216a344c7c83a3ea4ee74748",
      "whale": "Yuzu",
      "chain": "plasma",
      "debank_usd": 1467454.1308158152,
      "modeled_usd": 1474988.7212541997,
      "delta_usd": -7534.590438384563,
      "active_for_position_scan": true,
      "scan_threshold_usd": 50000,
      "below_threshold": false,
      "classification": "needs-review",
      "protocols_missing_or_misaligned": [
        {
          "protocol": "aave",
          "debank_usd": 1467454.1308139116,
          "modeled_usd": 1474988.7212541997,
          "delta_usd": -7534.590440288186
        }
      ]
    },
    {
      "wallet": "0x815f5bb257e88b67216a344c7c83a3ea4ee74748",
      "whale": "Yuzu",
      "chain": "uni",
      "debank_usd": 0.000017001700170017,
      "modeled_usd": 0,
      "delta_usd": 0.000017001700170017,
      "active_for_position_scan": false,
      "scan_threshold_usd": 50000,
      "below_threshold": true,
      "classification": "below-threshold",
      "protocols_missing_or_misaligned": []
    },
    {
      "wallet": "0x015cc48cc8bc37d80aaff4e43061dbaf94192308",
      "whale": "Yuzu",
      "chain": "eth",
      "debank_usd": 9075665.279755492,
      "modeled_usd": 0,
      "delta_usd": 9075665.279755492,
      "active_for_position_scan": true,
      "scan_threshold_usd": 50000,
      "below_threshold": false,
      "classification": "needs-review",
      "protocols_missing_or_misaligned": [
        {
          "protocol": "morpho",
          "debank_usd": 9069563.756012676,
          "modeled_usd": 0,
          "delta_usd": 9069563.756012676
        }
      ]
    },
    {
      "wallet": "0x015cc48cc8bc37d80aaff4e43061dbaf94192308",
      "whale": "Yuzu",
      "chain": "mnt",
      "debank_usd": 482698.1876501022,
      "modeled_usd": 495635.91776421014,
      "delta_usd": -12937.730114107952,
      "active_for_position_scan": true,
      "scan_threshold_usd": 50000,
      "below_threshold": false,
      "classification": "needs-review",
      "protocols_missing_or_misaligned": [
        {
          "protocol": "aave",
          "debank_usd": 482698.1876501022,
          "modeled_usd": 495635.91776421014,
          "delta_usd": -12937.730114107952
        }
      ]
    },
    {
      "wallet": "0x015cc48cc8bc37d80aaff4e43061dbaf94192308",
      "whale": "Yuzu",
      "chain": "plasma",
      "debank_usd": 1.3522528588402132,
      "modeled_usd": 0,
      "delta_usd": 1.3522528588402132,
      "active_for_position_scan": false,
      "scan_threshold_usd": 50000,
      "below_threshold": true,
      "classification": "below-threshold",
      "protocols_missing_or_misaligned": []
    },
    {
      "wallet": "0x502d222e8e4daef69032f55f0c1a999effd78fb3",
      "whale": "Yuzu",
      "chain": "megaeth",
      "debank_usd": 1779233.6325985044,
      "modeled_usd": 0,
      "delta_usd": 1779233.6325985044,
      "active_for_position_scan": true,
      "scan_threshold_usd": 50000,
      "below_threshold": false,
      "classification": "needs-review",
      "protocols_missing_or_misaligned": [
        {
          "protocol": "megaeth_aave3",
          "debank_usd": 1779233.6325985044,
          "modeled_usd": 0,
          "delta_usd": 1779233.6325985044
        }
      ]
    },
    {
      "wallet": "0x502d222e8e4daef69032f55f0c1a999effd78fb3",
      "whale": "Yuzu",
      "chain": "mnt",
      "debank_usd": 3646111.9753345526,
      "modeled_usd": 3667205.7278536,
      "delta_usd": -21093.752519047353,
      "active_for_position_scan": true,
      "scan_threshold_usd": 50000,
      "below_threshold": false,
      "classification": "needs-review",
      "protocols_missing_or_misaligned": [
        {
          "protocol": "aave",
          "debank_usd": 3643818.418398354,
          "modeled_usd": 3667205.7278536,
          "delta_usd": -23387.309455245733
        }
      ]
    },
    {
      "wallet": "0x502d222e8e4daef69032f55f0c1a999effd78fb3",
      "whale": "Yuzu",
      "chain": "eth",
      "debank_usd": 3585292.353094699,
      "modeled_usd": 3570190.9465817027,
      "delta_usd": 15101.406512996182,
      "active_for_position_scan": true,
      "scan_threshold_usd": 50000,
      "below_threshold": false,
      "classification": "needs-review",
      "protocols_missing_or_misaligned": [
        {
          "protocol": "morpho",
          "debank_usd": 3583246.8022785857,
          "modeled_usd": 3570190.9465817027,
          "delta_usd": 13055.855696883053
        }
      ]
    },
    {
      "wallet": "0x502d222e8e4daef69032f55f0c1a999effd78fb3",
      "whale": "Yuzu",
      "chain": "plasma",
      "debank_usd": 0,
      "modeled_usd": 0,
      "delta_usd": 0,
      "active_for_position_scan": false,
      "scan_threshold_usd": 50000,
      "below_threshold": true,
      "classification": "below-threshold",
      "protocols_missing_or_misaligned": []
    },
    {
      "wallet": "0xcf0a12cbd8088fc5f84ad431e71787157041cd69",
      "whale": "Yuzu",
      "chain": "eth",
      "debank_usd": 4337798.162733834,
      "modeled_usd": 4320895.977050599,
      "delta_usd": 16902.185683235526,
      "active_for_position_scan": true,
      "scan_threshold_usd": 50000,
      "below_threshold": false,
      "classification": "needs-review",
      "protocols_missing_or_misaligned": [
        {
          "protocol": "morpho",
          "debank_usd": 4337795.059181783,
          "modeled_usd": 4320895.977050599,
          "delta_usd": 16899.082131184638
        }
      ]
    },
    {
      "wallet": "0xcf0a12cbd8088fc5f84ad431e71787157041cd69",
      "whale": "Yuzu",
      "chain": "plasma",
      "debank_usd": 102305.16529541444,
      "modeled_usd": 103581.14763115998,
      "delta_usd": -1275.9823357455462,
      "active_for_position_scan": true,
      "scan_threshold_usd": 50000,
      "below_threshold": false,
      "classification": "aligned",
      "protocols_missing_or_misaligned": []
    },
    {
      "wallet": "0xb6cbe8b123392ef6aa72897bb85bd6515d2e8db7",
      "whale": "Yuzu",
      "chain": "eth",
      "debank_usd": 3967354.494897845,
      "modeled_usd": 3970794.6320470013,
      "delta_usd": -3440.1371491560712,
      "active_for_position_scan": true,
      "scan_threshold_usd": 50000,
      "below_threshold": false,
      "classification": "aligned",
      "protocols_missing_or_misaligned": []
    },
    {
      "wallet": "0xfaa7744b9ed973290a36ee815b5acc76856583a0",
      "whale": "Yuzu",
      "chain": "eth",
      "debank_usd": 6035286.142685213,
      "modeled_usd": 947615.3682948407,
      "delta_usd": 5087670.774390372,
      "active_for_position_scan": true,
      "scan_threshold_usd": 50000,
      "below_threshold": false,
      "classification": "needs-review",
      "protocols_missing_or_misaligned": [
        {
          "protocol": "upshift",
          "debank_usd": 5086805.620886088,
          "modeled_usd": 0,
          "delta_usd": 5086805.620886088
        }
      ]
    },
    {
      "wallet": "0x424323d25d30c687bdf79bb333da1d41c0373f37",
      "whale": "Yuzu",
      "chain": "eth",
      "debank_usd": 4.169533184316052e-12,
      "modeled_usd": 0,
      "delta_usd": 4.169533184316052e-12,
      "active_for_position_scan": false,
      "scan_threshold_usd": 50000,
      "below_threshold": true,
      "classification": "below-threshold",
      "protocols_missing_or_misaligned": []
    },
    {
      "wallet": "0xdaef005ae017be5b938a2b321db3dec96e684f68",
      "whale": "Yuzu",
      "chain": "plasma",
      "debank_usd": 409582.24201217905,
      "modeled_usd": 408568.661942058,
      "delta_usd": 1013.5800701210392,
      "active_for_position_scan": true,
      "scan_threshold_usd": 50000,
      "below_threshold": false,
      "classification": "aligned",
      "protocols_missing_or_misaligned": []
    },
    {
      "wallet": "0x6695c0f8706c5ace3bdf8995073179cca47926dc",
      "whale": "Yuzu",
      "chain": "plasma",
      "debank_usd": 465905.69881435466,
      "modeled_usd": 1026487.345985835,
      "delta_usd": -560581.6471714803,
      "active_for_position_scan": true,
      "scan_threshold_usd": 50000,
      "below_threshold": false,
      "classification": "needs-review",
      "protocols_missing_or_misaligned": [
        {
          "protocol": "yuzumoney",
          "debank_usd": 465905.69881435466,
          "modeled_usd": 150282.09214,
          "delta_usd": 315623.60667435464
        }
      ]
    },
    {
      "wallet": "0x09bfbc374c37c927909a0e7b278ee7fdf47a380a",
      "whale": "Yuzu",
      "chain": "monad",
      "debank_usd": 1019.2593404825392,
      "modeled_usd": 0,
      "delta_usd": 1019.2593404825392,
      "active_for_position_scan": false,
      "scan_threshold_usd": 50000,
      "below_threshold": true,
      "classification": "below-threshold",
      "protocols_missing_or_misaligned": []
    },
    {
      "wallet": "0x09bfbc374c37c927909a0e7b278ee7fdf47a380a",
      "whale": "Yuzu",
      "chain": "plasma",
      "debank_usd": 1050739.2048597713,
      "modeled_usd": 1050709.6751105397,
      "delta_usd": 29.529749231645837,
      "active_for_position_scan": true,
      "scan_threshold_usd": 50000,
      "below_threshold": false,
      "classification": "needs-review",
      "protocols_missing_or_misaligned": [
        {
          "protocol": "curve",
          "debank_usd": 799687.9077374811,
          "modeled_usd": 0,
          "delta_usd": 799687.9077374811
        }
      ]
    },
    {
      "wallet": "0x31eae643b679a84b37e3d0b4bd4f5da90fb04a61",
      "whale": "Reservoir",
      "chain": "eth",
      "debank_usd": 45554.006920005115,
      "modeled_usd": 0,
      "delta_usd": 45554.006920005115,
      "active_for_position_scan": false,
      "scan_threshold_usd": 50000,
      "below_threshold": true,
      "classification": "below-threshold",
      "protocols_missing_or_misaligned": [
        {
          "protocol": "morpho",
          "debank_usd": 45554.006920005115,
          "modeled_usd": 0,
          "delta_usd": 45554.006920005115
        }
      ]
    },
    {
      "wallet": "0x3063c5907faa10c01b242181aa689beb23d2bd65",
      "whale": "Reservoir",
      "chain": "eth",
      "debank_usd": 62547299.126350015,
      "modeled_usd": 62542138.01852065,
      "delta_usd": 5161.107829362154,
      "active_for_position_scan": true,
      "scan_threshold_usd": 50000,
      "below_threshold": false,
      "classification": "needs-review",
      "protocols_missing_or_misaligned": [
        {
          "protocol": "aave",
          "debank_usd": 5981640.20352804,
          "modeled_usd": 0,
          "delta_usd": 5981640.20352804
        }
      ]
    },
    {
      "wallet": "0x3063c5907faa10c01b242181aa689beb23d2bd65",
      "whale": "Reservoir",
      "chain": "plasma",
      "debank_usd": 0.00002820945958165125,
      "modeled_usd": 0,
      "delta_usd": 0.00002820945958165125,
      "active_for_position_scan": false,
      "scan_threshold_usd": 50000,
      "below_threshold": true,
      "classification": "below-threshold",
      "protocols_missing_or_misaligned": []
    },
    {
      "wallet": "0x289c204b35859bfb924b9c0759a4fe80f610671c",
      "whale": "Reservoir",
      "chain": "eth",
      "debank_usd": 30782365.792525154,
      "modeled_usd": 30772764.6531034,
      "delta_usd": 9601.139421753585,
      "active_for_position_scan": true,
      "scan_threshold_usd": 50000,
      "below_threshold": false,
      "classification": "needs-review",
      "protocols_missing_or_misaligned": [
        {
          "protocol": "morpho",
          "debank_usd": 30782365.792524196,
          "modeled_usd": 30772764.6531034,
          "delta_usd": 9601.139420796186
        }
      ]
    },
    {
      "wallet": "0x289c204b35859bfb924b9c0759a4fe80f610671c",
      "whale": "Reservoir",
      "chain": "katana",
      "debank_usd": 5002721.156845684,
      "modeled_usd": 0,
      "delta_usd": 5002721.156845684,
      "active_for_position_scan": true,
      "scan_threshold_usd": 50000,
      "below_threshold": false,
      "classification": "needs-review",
      "protocols_missing_or_misaligned": [
        {
          "protocol": "katana_morphoblue",
          "debank_usd": 5002721.156845684,
          "modeled_usd": 0,
          "delta_usd": 5002721.156845684
        }
      ]
    },
    {
      "wallet": "0x289c204b35859bfb924b9c0759a4fe80f610671c",
      "whale": "Reservoir",
      "chain": "mnt",
      "debank_usd": 3.494675159329973,
      "modeled_usd": 0,
      "delta_usd": 3.494675159329973,
      "active_for_position_scan": false,
      "scan_threshold_usd": 50000,
      "below_threshold": true,
      "classification": "below-threshold",
      "protocols_missing_or_misaligned": []
    },
    {
      "wallet": "0x289c204b35859bfb924b9c0759a4fe80f610671c",
      "whale": "Reservoir",
      "chain": "monad",
      "debank_usd": 6003833.420566874,
      "modeled_usd": 6004567.46574556,
      "delta_usd": -734.0451786862686,
      "active_for_position_scan": true,
      "scan_threshold_usd": 50000,
      "below_threshold": false,
      "classification": "aligned",
      "protocols_missing_or_misaligned": []
    },
    {
      "wallet": "0xd1a1c248b253f1fc60eacd90777b9a63f8c8c1bc",
      "whale": "Makina",
      "chain": "eth",
      "debank_usd": 7073306.115465965,
      "modeled_usd": 5407620.260098321,
      "delta_usd": 1665685.8553676438,
      "active_for_position_scan": true,
      "scan_threshold_usd": 50000,
      "below_threshold": false,
      "classification": "needs-review",
      "protocols_missing_or_misaligned": [
        {
          "protocol": "aave",
          "debank_usd": 2636720.4998892793,
          "modeled_usd": 1013113.6858069,
          "delta_usd": 1623606.8140823792
        },
        {
          "protocol": "infinifixyz",
          "debank_usd": 1440972.7941868044,
          "modeled_usd": 0,
          "delta_usd": 1440972.7941868044
        },
        {
          "protocol": "convex",
          "debank_usd": 227430.82304901222,
          "modeled_usd": 0,
          "delta_usd": 227430.82304901222
        }
      ]
    },
    {
      "wallet": "0xbeef123217647014429b7670329782e210884e89",
      "whale": "Makina",
      "chain": "base",
      "debank_usd": 1510484.7598709872,
      "modeled_usd": 1510073.65929169,
      "delta_usd": 411.10057929717004,
      "active_for_position_scan": true,
      "scan_threshold_usd": 50000,
      "below_threshold": false,
      "classification": "needs-review",
      "protocols_missing_or_misaligned": [
        {
          "protocol": "base_morphoblue",
          "debank_usd": 1510484.7598709872,
          "modeled_usd": 0,
          "delta_usd": 1510484.7598709872
        }
      ]
    },
    {
      "wallet": "0xbeef123217647014429b7670329782e210884e89",
      "whale": "Makina",
      "chain": "eth",
      "debank_usd": 6351279.9028406255,
      "modeled_usd": 6332022.021126033,
      "delta_usd": 19257.881714592688,
      "active_for_position_scan": true,
      "scan_threshold_usd": 50000,
      "below_threshold": false,
      "classification": "needs-review",
      "protocols_missing_or_misaligned": [
        {
          "protocol": "morpho",
          "debank_usd": 6316197.561358258,
          "modeled_usd": 3355340.798836859,
          "delta_usd": 2960856.762521399
        },
        {
          "protocol": "sky",
          "debank_usd": 35082.34148236744,
          "modeled_usd": 0,
          "delta_usd": 35082.34148236744
        }
      ]
    },
    {
      "wallet": "0x76d2e84009dae457f8667d823c7c96e9a7c35b78",
      "whale": "InfiniFi",
      "chain": "eth",
      "debank_usd": 3519239.4093219317,
      "modeled_usd": 3513228.17526259,
      "delta_usd": 6011.2340593417175,
      "active_for_position_scan": true,
      "scan_threshold_usd": 50000,
      "below_threshold": false,
      "classification": "aligned",
      "protocols_missing_or_misaligned": []
    },
    {
      "wallet": "0x7e9aa426abc2d9006e8c9881754baa00a392158d",
      "whale": "InfiniFi",
      "chain": "eth",
      "debank_usd": 2709.8200999977453,
      "modeled_usd": 1864.395732,
      "delta_usd": 845.4243679977453,
      "active_for_position_scan": false,
      "scan_threshold_usd": 50000,
      "below_threshold": true,
      "classification": "below-threshold",
      "protocols_missing_or_misaligned": []
    },
    {
      "wallet": "0xd880d7c5cafdbe2aec281250995abf612235e563",
      "whale": "InfiniFi",
      "chain": "eth",
      "debank_usd": 9889126.152079208,
      "modeled_usd": 9880852.94076309,
      "delta_usd": 8273.211316118017,
      "active_for_position_scan": true,
      "scan_threshold_usd": 50000,
      "below_threshold": false,
      "classification": "needs-review",
      "protocols_missing_or_misaligned": [
        {
          "protocol": "spark",
          "debank_usd": 9889126.152079208,
          "modeled_usd": 9880852.94076309,
          "delta_usd": 8273.211316118017
        }
      ]
    },
    {
      "wallet": "0x817d93dbdfd8190bbef0a73fcf5dd9da5a87e032",
      "whale": "InfiniFi",
      "chain": "eth",
      "debank_usd": 762642.782760276,
      "modeled_usd": 762392.705515879,
      "delta_usd": 250.07724439701997,
      "active_for_position_scan": true,
      "scan_threshold_usd": 50000,
      "below_threshold": false,
      "classification": "aligned",
      "protocols_missing_or_misaligned": []
    },
    {
      "wallet": "0xbfd5fc8deca3c6128bfce0fe46c25616811c3580",
      "whale": "InfiniFi",
      "chain": "eth",
      "debank_usd": 0.07869286928692869,
      "modeled_usd": 0,
      "delta_usd": 0.07869286928692869,
      "active_for_position_scan": false,
      "scan_threshold_usd": 50000,
      "below_threshold": true,
      "classification": "below-threshold",
      "protocols_missing_or_misaligned": []
    },
    {
      "wallet": "0xf014ef13a3e0372582f44a667e144a4f2e439ea7",
      "whale": "Upshift",
      "chain": "eth",
      "debank_usd": 9438716.852270856,
      "modeled_usd": 6422909.720322582,
      "delta_usd": 3015807.1319482746,
      "active_for_position_scan": true,
      "scan_threshold_usd": 50000,
      "below_threshold": false,
      "classification": "needs-review",
      "protocols_missing_or_misaligned": [
        {
          "protocol": "upshift",
          "debank_usd": 3222884.7262066207,
          "modeled_usd": 0,
          "delta_usd": 3222884.7262066207
        }
      ]
    },
    {
      "wallet": "0x9f1a1479191af103ff82fead23e950b6b3b2bd1a",
      "whale": "Upshift",
      "chain": "eth",
      "debank_usd": 21062451.466744326,
      "modeled_usd": 21027510.122378383,
      "delta_usd": 34941.34436594322,
      "active_for_position_scan": true,
      "scan_threshold_usd": 50000,
      "below_threshold": false,
      "classification": "needs-review",
      "protocols_missing_or_misaligned": [
        {
          "protocol": "morpho",
          "debank_usd": 21061630.428758115,
          "modeled_usd": 21027510.122378383,
          "delta_usd": 34120.306379731745
        }
      ]
    },
    {
      "wallet": "0x9f1a1479191af103ff82fead23e950b6b3b2bd1a",
      "whale": "Upshift",
      "chain": "monad",
      "debank_usd": 13308104.335377097,
      "modeled_usd": 12630839.207583824,
      "delta_usd": 677265.127793273,
      "active_for_position_scan": true,
      "scan_threshold_usd": 50000,
      "below_threshold": false,
      "classification": "needs-review",
      "protocols_missing_or_misaligned": [
        {
          "protocol": "curvance",
          "debank_usd": 4348251.040159951,
          "modeled_usd": 3217125.33484609,
          "delta_usd": 1131125.705313861
        }
      ]
    },
    {
      "wallet": "0x6f64630a0c12c60813a80a215fb9a31e52528820",
      "whale": "Upshift",
      "chain": "avax",
      "debank_usd": 503821.99615015165,
      "modeled_usd": 503595.1306778089,
      "delta_usd": 226.86547234276077,
      "active_for_position_scan": true,
      "scan_threshold_usd": 50000,
      "below_threshold": false,
      "classification": "aligned",
      "protocols_missing_or_misaligned": []
    },
    {
      "wallet": "0x6f64630a0c12c60813a80a215fb9a31e52528820",
      "whale": "Upshift",
      "chain": "eth",
      "debank_usd": 1471324.4739199032,
      "modeled_usd": 1471092.895973972,
      "delta_usd": 231.57794593111612,
      "active_for_position_scan": true,
      "scan_threshold_usd": 50000,
      "below_threshold": false,
      "classification": "aligned",
      "protocols_missing_or_misaligned": []
    },
    {
      "wallet": "0x6f64630a0c12c60813a80a215fb9a31e52528820",
      "whale": "Upshift",
      "chain": "monad",
      "debank_usd": 835678.3528355465,
      "modeled_usd": 835349.550333312,
      "delta_usd": 328.8025022344664,
      "active_for_position_scan": true,
      "scan_threshold_usd": 50000,
      "below_threshold": false,
      "classification": "aligned",
      "protocols_missing_or_misaligned": []
    },
    {
      "wallet": "0x6f64630a0c12c60813a80a215fb9a31e52528820",
      "whale": "Upshift",
      "chain": "plasma",
      "debank_usd": 563004.3421606233,
      "modeled_usd": 563526.42397764,
      "delta_usd": -522.081817016704,
      "active_for_position_scan": true,
      "scan_threshold_usd": 50000,
      "below_threshold": false,
      "classification": "aligned",
      "protocols_missing_or_misaligned": []
    },
    {
      "wallet": "0x68e7e72938db36a5cbbca7b52c71dbbaadfb8264",
      "whale": "Midas",
      "chain": "eth",
      "debank_usd": 11934914.780050945,
      "modeled_usd": 5261694.832970287,
      "delta_usd": 6673219.947080658,
      "active_for_position_scan": true,
      "scan_threshold_usd": 50000,
      "below_threshold": false,
      "classification": "needs-review",
      "protocols_missing_or_misaligned": [
        {
          "protocol": "fluid",
          "debank_usd": 6669493.847842784,
          "modeled_usd": 0,
          "delta_usd": 6669493.847842784
        },
        {
          "protocol": "sky",
          "debank_usd": 1400857.9454114866,
          "modeled_usd": 0,
          "delta_usd": 1400857.9454114866
        }
      ]
    },
    {
      "wallet": "0x68e7e72938db36a5cbbca7b52c71dbbaadfb8264",
      "whale": "Midas",
      "chain": "arb",
      "debank_usd": 10881928.04050392,
      "modeled_usd": 10876892.93148184,
      "delta_usd": 5035.109022079036,
      "active_for_position_scan": true,
      "scan_threshold_usd": 50000,
      "below_threshold": false,
      "classification": "needs-review",
      "protocols_missing_or_misaligned": [
        {
          "protocol": "arb_usdai",
          "debank_usd": 10586341.402070388,
          "modeled_usd": 0,
          "delta_usd": 10586341.402070388
        }
      ]
    },
    {
      "wallet": "0x68e7e72938db36a5cbbca7b52c71dbbaadfb8264",
      "whale": "Midas",
      "chain": "hyper",
      "debank_usd": 0.5914833144081,
      "modeled_usd": 0,
      "delta_usd": 0.5914833144081,
      "active_for_position_scan": false,
      "scan_threshold_usd": 50000,
      "below_threshold": true,
      "classification": "below-threshold",
      "protocols_missing_or_misaligned": []
    },
    {
      "wallet": "0x68e7e72938db36a5cbbca7b52c71dbbaadfb8264",
      "whale": "Midas",
      "chain": "megaeth",
      "debank_usd": 955031.3449335676,
      "modeled_usd": 0,
      "delta_usd": 955031.3449335676,
      "active_for_position_scan": true,
      "scan_threshold_usd": 50000,
      "below_threshold": false,
      "classification": "needs-review",
      "protocols_missing_or_misaligned": [
        {
          "protocol": "megaeth_aave3",
          "debank_usd": 955031.3449335676,
          "modeled_usd": 0,
          "delta_usd": 955031.3449335676
        }
      ]
    },
    {
      "wallet": "0x68e7e72938db36a5cbbca7b52c71dbbaadfb8264",
      "whale": "Midas",
      "chain": "monad",
      "debank_usd": 2155093.068741934,
      "modeled_usd": 2154482.97275091,
      "delta_usd": 610.0959910238162,
      "active_for_position_scan": true,
      "scan_threshold_usd": 50000,
      "below_threshold": false,
      "classification": "aligned",
      "protocols_missing_or_misaligned": []
    },
    {
      "wallet": "0x68e7e72938db36a5cbbca7b52c71dbbaadfb8264",
      "whale": "Midas",
      "chain": "plasma",
      "debank_usd": 129317.34876522396,
      "modeled_usd": 129324.651600401,
      "delta_usd": -7.3028351770481095,
      "active_for_position_scan": true,
      "scan_threshold_usd": 50000,
      "below_threshold": false,
      "classification": "aligned",
      "protocols_missing_or_misaligned": []
    },
    {
      "wallet": "0x70ac345ab736ce145e0d4b5deced7a8bcb0e4033",
      "whale": "Midas",
      "chain": "arb",
      "debank_usd": 4814108.606629353,
      "modeled_usd": 4813397.948547486,
      "delta_usd": 710.6580818668008,
      "active_for_position_scan": true,
      "scan_threshold_usd": 50000,
      "below_threshold": false,
      "classification": "aligned",
      "protocols_missing_or_misaligned": []
    },
    {
      "wallet": "0x70ac345ab736ce145e0d4b5deced7a8bcb0e4033",
      "whale": "Midas",
      "chain": "avax",
      "debank_usd": 72.78300128596814,
      "modeled_usd": 0,
      "delta_usd": 72.78300128596814,
      "active_for_position_scan": false,
      "scan_threshold_usd": 50000,
      "below_threshold": true,
      "classification": "below-threshold",
      "protocols_missing_or_misaligned": []
    },
    {
      "wallet": "0x70ac345ab736ce145e0d4b5deced7a8bcb0e4033",
      "whale": "Midas",
      "chain": "base",
      "debank_usd": 1002882.4787273599,
      "modeled_usd": 1002037.95330537,
      "delta_usd": 844.5254219898488,
      "active_for_position_scan": true,
      "scan_threshold_usd": 50000,
      "below_threshold": false,
      "classification": "needs-review",
      "protocols_missing_or_misaligned": [
        {
          "protocol": "base_fluid",
          "debank_usd": 1002882.4787273599,
          "modeled_usd": 0,
          "delta_usd": 1002882.4787273599
        }
      ]
    },
    {
      "wallet": "0x70ac345ab736ce145e0d4b5deced7a8bcb0e4033",
      "whale": "Midas",
      "chain": "eth",
      "debank_usd": 10414218.586103773,
      "modeled_usd": 10409676.670034356,
      "delta_usd": 4541.916069416329,
      "active_for_position_scan": true,
      "scan_threshold_usd": 50000,
      "below_threshold": false,
      "classification": "aligned",
      "protocols_missing_or_misaligned": []
    },
    {
      "wallet": "0x70ac345ab736ce145e0d4b5deced7a8bcb0e4033",
      "whale": "Midas",
      "chain": "monad",
      "debank_usd": 1654478.2838844364,
      "modeled_usd": 1653598.96390871,
      "delta_usd": 879.3199757263064,
      "active_for_position_scan": true,
      "scan_threshold_usd": 50000,
      "below_threshold": false,
      "classification": "aligned",
      "protocols_missing_or_misaligned": []
    },
    {
      "wallet": "0x70ac345ab736ce145e0d4b5deced7a8bcb0e4033",
      "whale": "Midas",
      "chain": "plasma",
      "debank_usd": 1014488.0320303071,
      "modeled_usd": 1014201.54097042,
      "delta_usd": 286.49105988710653,
      "active_for_position_scan": true,
      "scan_threshold_usd": 50000,
      "below_threshold": false,
      "classification": "aligned",
      "protocols_missing_or_misaligned": []
    },
    {
      "wallet": "0x461263bff57cbafe3994b15a5e4d388c50d4d9fe",
      "whale": "Midas",
      "chain": "plasma",
      "debank_usd": 0,
      "modeled_usd": 0,
      "delta_usd": 0,
      "active_for_position_scan": false,
      "scan_threshold_usd": 50000,
      "below_threshold": true,
      "classification": "below-threshold",
      "protocols_missing_or_misaligned": []
    },
    {
      "wallet": "0x0fe15b65136ab92a3f9ce83cceb9e0663f1efaa6",
      "whale": "Midas",
      "chain": "eth",
      "debank_usd": 0.000004041536220457714,
      "modeled_usd": 0,
      "delta_usd": 0.000004041536220457714,
      "active_for_position_scan": false,
      "scan_threshold_usd": 50000,
      "below_threshold": true,
      "classification": "below-threshold",
      "protocols_missing_or_misaligned": []
    },
    {
      "wallet": "0xd6c757043e7d59088969b188923c62fa960afe9b",
      "whale": "Midas",
      "chain": "arb",
      "debank_usd": 0.01016710341416149,
      "modeled_usd": 0,
      "delta_usd": 0.01016710341416149,
      "active_for_position_scan": false,
      "scan_threshold_usd": 50000,
      "below_threshold": true,
      "classification": "below-threshold",
      "protocols_missing_or_misaligned": []
    },
    {
      "wallet": "0xd6c757043e7d59088969b188923c62fa960afe9b",
      "whale": "Midas",
      "chain": "bsc",
      "debank_usd": 2141795.0409383285,
      "modeled_usd": 2460786.765796179,
      "delta_usd": -318991.72485785047,
      "active_for_position_scan": true,
      "scan_threshold_usd": 50000,
      "below_threshold": false,
      "classification": "needs-review",
      "protocols_missing_or_misaligned": [
        {
          "protocol": "bsc_venusflux",
          "debank_usd": 2141795.0409383285,
          "modeled_usd": 2460786.765796179,
          "delta_usd": -318991.72485785047
        }
      ]
    },
    {
      "wallet": "0xd6c757043e7d59088969b188923c62fa960afe9b",
      "whale": "Midas",
      "chain": "eth",
      "debank_usd": 9019619.038501339,
      "modeled_usd": 7746255.75101478,
      "delta_usd": 1273363.2874865588,
      "active_for_position_scan": true,
      "scan_threshold_usd": 50000,
      "below_threshold": false,
      "classification": "needs-review",
      "protocols_missing_or_misaligned": [
        {
          "protocol": "morpho",
          "debank_usd": 3845472.604748514,
          "modeled_usd": 2586683.0700411308,
          "delta_usd": 1258789.5347073833
        },
        {
          "protocol": "euler",
          "debank_usd": 5165455.6233125925,
          "modeled_usd": 5159572.68097365,
          "delta_usd": 5882.94233894255
        }
      ]
    },
    {
      "wallet": "0xd6c757043e7d59088969b188923c62fa960afe9b",
      "whale": "Midas",
      "chain": "plasma",
      "debank_usd": 0.01112444551024793,
      "modeled_usd": 0,
      "delta_usd": 0.01112444551024793,
      "active_for_position_scan": false,
      "scan_threshold_usd": 50000,
      "below_threshold": true,
      "classification": "below-threshold",
      "protocols_missing_or_misaligned": []
    },
    {
      "wallet": "0x41a9eb398518d2487301c61d2b33e4e966a9f1dd",
      "whale": "Superform",
      "chain": "eth",
      "debank_usd": 12800680.137761611,
      "modeled_usd": 6352709.669267998,
      "delta_usd": 6447970.468493613,
      "active_for_position_scan": true,
      "scan_threshold_usd": 50000,
      "below_threshold": false,
      "classification": "needs-review",
      "protocols_missing_or_misaligned": [
        {
          "protocol": "morpho",
          "debank_usd": 12799755.484141411,
          "modeled_usd": 6352709.669267998,
          "delta_usd": 6447045.814873413
        }
      ]
    },
    {
      "wallet": "0x9ea38e09f41a9de53972a68268ba0dcc6d2fadf8",
      "whale": "Re Protocol",
      "chain": "eth",
      "debank_usd": 41493914.98004324,
      "modeled_usd": 41487874.444125,
      "delta_usd": 6040.535918243229,
      "active_for_position_scan": true,
      "scan_threshold_usd": 50000,
      "below_threshold": false,
      "classification": "needs-review",
      "protocols_missing_or_misaligned": [
        {
          "protocol": "ethena",
          "debank_usd": 41493914.98004324,
          "modeled_usd": 0,
          "delta_usd": 41493914.98004324
        }
      ]
    },
    {
      "wallet": "0x295f67fdb21255a3db82964445628a706fbe689e",
      "whale": "Re Protocol",
      "chain": "base",
      "debank_usd": 40.235534837115026,
      "modeled_usd": 0,
      "delta_usd": 40.235534837115026,
      "active_for_position_scan": false,
      "scan_threshold_usd": 50000,
      "below_threshold": true,
      "classification": "below-threshold",
      "protocols_missing_or_misaligned": []
    },
    {
      "wallet": "0x295f67fdb21255a3db82964445628a706fbe689e",
      "whale": "Re Protocol",
      "chain": "eth",
      "debank_usd": 22168562.87028851,
      "modeled_usd": 36315075.40271577,
      "delta_usd": -14146512.532427263,
      "active_for_position_scan": true,
      "scan_threshold_usd": 50000,
      "below_threshold": false,
      "classification": "needs-review",
      "protocols_missing_or_misaligned": [
        {
          "protocol": "ethena",
          "debank_usd": 20757075.663374573,
          "modeled_usd": 0,
          "delta_usd": 20757075.663374573
        }
      ]
    },
    {
      "wallet": "0x5c454f5526e41fbe917b63475cd8ca7e4631b147",
      "whale": "Re Protocol",
      "chain": "eth",
      "debank_usd": 1809607.941885091,
      "modeled_usd": 1809285.30042734,
      "delta_usd": 322.64145775092766,
      "active_for_position_scan": true,
      "scan_threshold_usd": 50000,
      "below_threshold": false,
      "classification": "needs-review",
      "protocols_missing_or_misaligned": [
        {
          "protocol": "ethena",
          "debank_usd": 1809607.941885091,
          "modeled_usd": 0,
          "delta_usd": 1809607.941885091
        }
      ]
    },
    {
      "wallet": "0xd4374008c88321eb2e59abd311156c44b25831e9",
      "whale": "Re Protocol",
      "chain": "eth",
      "debank_usd": 1626936.9490184619,
      "modeled_usd": 3067206.00288062,
      "delta_usd": -1440269.053862158,
      "active_for_position_scan": true,
      "scan_threshold_usd": 50000,
      "below_threshold": false,
      "classification": "needs-review",
      "protocols_missing_or_misaligned": [
        {
          "protocol": "ethena",
          "debank_usd": 1626936.9490184619,
          "modeled_usd": 0,
          "delta_usd": 1626936.9490184619
        }
      ]
    },
    {
      "wallet": "0xe1886be2ba8b2496c2044a77516f63a734193082",
      "whale": "Re Protocol",
      "chain": "eth",
      "debank_usd": 258.7414284814112,
      "modeled_usd": 0,
      "delta_usd": 258.7414284814112,
      "active_for_position_scan": false,
      "scan_threshold_usd": 50000,
      "below_threshold": true,
      "classification": "below-threshold",
      "protocols_missing_or_misaligned": []
    }
  ]
}